aiohttp_validator/__init__.py
aiohttp_validator/validator.py
aiohttp_validator-0.2.0.dist-info/LICENSE
aiohttp_validator-0.2.0.dist-info/METADATA
aiohttp_validator-0.2.0.dist-info/WHEEL
aiohttp_validator-0.2.0.dist-info/RECORD
