Metadata-Version: 2.1
Name: aiohttp-validator
Version: 0.2.0
Summary: aiohttp simple pydantic validator
Home-page: https://github.com/dapper91/aiohttp-validator
License: Unlicense
Keywords: aiohttp,pydantic,validation,http,asyncio
Author: Dmitry Pershin
Author-email: dapper1291@gmail.com
Requires-Python: >=3.9
Classifier: Development Status :: 5 - Production/Stable
Classifier: Framework :: AsyncIO
Classifier: Framework :: Pydantic
Classifier: Framework :: Pydantic :: 2
Classifier: Intended Audience :: Developers
Classifier: License :: OSI Approved
Classifier: License :: Public Domain
Classifier: Programming Language :: Python :: 3
Classifier: Programming Language :: Python :: 3.9
Classifier: Programming Language :: Python :: 3.10
Classifier: Programming Language :: Python :: 3.11
Classifier: Topic :: Internet :: WWW/HTTP :: HTTP Servers
Classifier: Topic :: Software Development :: Libraries
Requires-Dist: aiohttp (>=3.7.0)
Requires-Dist: pydantic (>=2.0)
Project-URL: Repository, https://github.com/dapper91/aiohttp-validator
